README.md
setup.py
msgflow/__init__.py
msgflow/bot.py
msgflow/config.py
msgflow/content.py
msgflow/logging.py
msgflow/main.py
msgflow/memory.py
msgflow/protocol.py
msgflow.egg-info/PKG-INFO
msgflow.egg-info/SOURCES.txt
msgflow.egg-info/dependency_links.txt
msgflow.egg-info/requires.txt
msgflow.egg-info/top_level.txt
msgflow/service/__init__.py
msgflow/service/_twitter_mentions_timeline_service.py
msgflow/service/cli_service.py
msgflow/service/cron_service.py
msgflow/service/slack_service.py
msgflow/service/twitter_service.py
msgflow/service/webapi_service.py