Metadata-Version: 2.1
Name: msgflow
Version: 0.6.0
Summary: msgFlow is a simple chatbot framework for simple configuration, customization and connection with several services.
Home-page: https://github.com/colorfulscoop/msgflow
Author: Noriyuki Abe
License: UNKNOWN
Platform: UNKNOWN
Classifier: Programming Language :: Python :: 3.9
Classifier: License :: OSI Approved :: MIT License
Classifier: Operating System :: OS Independent
Provides-Extra: test
Provides-Extra: webapi
Provides-Extra: slack
Provides-Extra: cron
